pydify/__init__.py
pydify/agent.py
pydify/chatbot.py
pydify/chatflow.py
pydify/common.py
pydify/config.py
pydify/site.py
pydify/text_generation.py
pydify/workflow.py
pydify-2.4.0.dist-info/licenses/LICENSE
pydify-2.4.0.dist-info/METADATA
pydify-2.4.0.dist-info/WHEEL
pydify-2.4.0.dist-info/top_level.txt
pydify-2.4.0.dist-info/RECORD
